image3c/__init__.py
image3c/imageprep.py
image3c/infer_classifier.py
image3c/network.py
image3c/network_training.py
image3c/read_cif.py
image3c/utils.py
image3c-0.1.4.dist-info/METADATA
image3c-0.1.4.dist-info/WHEEL
image3c-0.1.4.dist-info/top_level.txt
image3c-0.1.4.dist-info/RECORD
