Metadata-Version: 2.1
Name: image3c
Version: 0.1.4
Summary: Classifier for Image3c
Home-page: https://github.com/stowersinstitute/LIBPB-1390-Image3C
Author: Chris Wood
Author-email: cjw@stowers.org
License: Apache Software License 2.0
Classifier: Development Status :: 4 - Beta
Classifier: Intended Audience :: Developers
Classifier: Topic :: Software Development :: Testing
Classifier: Programming Language :: Python
Classifier: Programming Language :: Python :: 3.7
Classifier: Operating System :: OS Independent
Classifier: License :: OSI Approved :: Apache Software License
Requires-Python: >=3.6,<3.8
